Metadata-Version: 1.1
Name: letipy
Version: 0.1.0
Summary: A Powerful scientific strings-processing library
Home-page: UNKNOWN
Author: Khalid Aghrini
Author-email: kwaaghrini@gmail.com
License: UNKNOWN
Platform: UNKNOWN
Classifier: Programming Language :: Python :: 3
Classifier: License :: OSI Approved :: MIT License
Classifier: Operating System :: OS Independent
